omnibenchmark/.gitignore
omnibenchmark/__init__.py
omnibenchmark/config.py
omnibenchmark/constants.py
omnibenchmark/sync.py
omnibenchmark/utils.py
omnibenchmark/benchmark/__init__.py
omnibenchmark/benchmark/benchmark.py
omnibenchmark/benchmark/benchmark_node.py
omnibenchmark/benchmark/constants.py
omnibenchmark/benchmark/converter.py
omnibenchmark/benchmark/dag.py
omnibenchmark/benchmark/params.py
omnibenchmark/benchmark/symlinks.py
omnibenchmark/benchmark/validation/__init__.py
omnibenchmark/benchmark/validation/error.py
omnibenchmark/benchmark/validation/validator.py
omnibenchmark/cli/benchmark.py
omnibenchmark/cli/debug.py
omnibenchmark/cli/io.py
omnibenchmark/cli/main.py
omnibenchmark/cli/run.py
omnibenchmark/cli/utils/__init__.py
omnibenchmark/cli/utils/args.py
omnibenchmark/cli/utils/logging.py
omnibenchmark/cli/utils/validation.py
omnibenchmark/io/MinIOStorage.py
omnibenchmark/io/README.md
omnibenchmark/io/RemoteStorage.py
omnibenchmark/io/S3config.py
omnibenchmark/io/S3versioning.py
omnibenchmark/io/__init__.py
omnibenchmark/io/archive.py
omnibenchmark/io/code.py
omnibenchmark/io/exception.py
omnibenchmark/io/files.py
omnibenchmark/io/hash.py
omnibenchmark/io/sizeof.py
omnibenchmark/io/storage.py
omnibenchmark/io/tree.py
omnibenchmark/io/versioning.py
omnibenchmark/model/__init__.py
omnibenchmark/model/module.py
omnibenchmark/workflow/__init__.py
omnibenchmark/workflow/workflow.py
omnibenchmark/workflow/snakemake/__init__.py
omnibenchmark/workflow/snakemake/snakemake.py
omnibenchmark/workflow/snakemake/format/__init__.py
omnibenchmark/workflow/snakemake/format/formatter.py
omnibenchmark/workflow/snakemake/rules/__init__.py
omnibenchmark/workflow/snakemake/rules/rule_all.smk
omnibenchmark/workflow/snakemake/rules/rule_node.smk
omnibenchmark/workflow/snakemake/rules/rule_start_benchmark.smk
omnibenchmark/workflow/snakemake/rules/utils.smk
omnibenchmark/workflow/snakemake/scripts/__init__.py
omnibenchmark/workflow/snakemake/scripts/execution.py
omnibenchmark-0.3.2.dist-info/licenses/LICENSE
omnibenchmark-0.3.2.dist-info/METADATA
omnibenchmark-0.3.2.dist-info/WHEEL
omnibenchmark-0.3.2.dist-info/entry_points.txt
omnibenchmark-0.3.2.dist-info/top_level.txt
omnibenchmark-0.3.2.dist-info/RECORD
