Metadata-Version: 2.4
Name: omnibenchmark
Version: 0.3.2
Summary: A tool for automated scientific benchmarking
Author: Reto Gerber, Ben Carrillo
Author-email: Almut Lütge <almut.lue@gmail.com>, Izaskun Mallona <izaskun.mallona@gmail.com>, Daniel Incicau <daniel.incicau@gmail.com>
Project-URL: Homepage, https://omnibenchmark.org
Project-URL: Repository, https://github.com/omnibenchmark/omnibenchmark
Classifier: Intended Audience :: Developers
Classifier: Intended Audience :: Science/Research
Classifier: License :: OSI Approved :: Apache Software License
Classifier: Operating System :: OS Independent
Classifier: Programming Language :: Python
Requires-Python: ~=3.12
License-File: LICENSE
Requires-Dist: click>=8.1.7
Requires-Dist: aiohttp>=3.9.5
Requires-Dist: async>=0.6.2
Requires-Dist: tqdm>=4.66.4
Requires-Dist: requests>=2.31.0
Requires-Dist: python-dateutil>=2.9.0.post0
Requires-Dist: filelock>=3.4.0
Requires-Dist: spdx-license-list>=3.19
Requires-Dist: PyYAML
Requires-Dist: humanfriendly
Requires-Dist: pydantic
Requires-Dist: networkx>=3.3
Requires-Dist: matplotlib==3.8.0
Requires-Dist: pydot>=3.0.2
Requires-Dist: GitPython>=3.1.0
Requires-Dist: snakemake>=8.0
Requires-Dist: easybuild>=5.0.0
Requires-Dist: easybuild-easyblocks>=5.0.0
Requires-Dist: omni-schema>=0.0.6
Requires-Dist: snakemake-executor-plugin-slurm<2.0.0,>=1.4.0
Provides-Extra: s3
Requires-Dist: minio>=7.2.7; extra == "s3"
Requires-Dist: boto3>=1.34.102; extra == "s3"
Requires-Dist: snakemake-storage-plugin-s3>=0.2.12; extra == "s3"
Provides-Extra: test
Requires-Dist: pytest-cov>=4.1.0; extra == "test"
Requires-Dist: pytest-split>=0.9.0; extra == "test"
Requires-Dist: pytest-xdist>=3.6.1; extra == "test"
Requires-Dist: testcontainers>=4.5.1; extra == "test"
Requires-Dist: pytest-timeout==2.3.1; extra == "test"
Requires-Dist: s3fs[boto3]>=2023.12.0; extra == "test"
Provides-Extra: dev
Requires-Dist: ipython; extra == "dev"
Requires-Dist: pre-commit; extra == "dev"
Requires-Dist: ruff; extra == "dev"
Requires-Dist: typing-extensions; extra == "dev"
Requires-Dist: isort; extra == "dev"
Requires-Dist: pyright; extra == "dev"
Dynamic: license-file
